examples/Basic.py
examples/CleanJump.py
examples/CleanScan.py
examples/CleanSweep+Scope.py
examples/CleanSweep.py
examples/FinetuneFrequency.py
examples/JumpSweep+Scope.py
examples/JumpSweep.py
examples/__init__.py
purephotonicscontrol/__init__.py
purephotonicscontrol/clean_scan_parameters.py
purephotonicscontrol/lasercommands.py
purephotonicscontrol/logger.py
purephotonicscontrol-0.0.0.dist-info/LICENSE
purephotonicscontrol-0.0.0.dist-info/METADATA
purephotonicscontrol-0.0.0.dist-info/WHEEL
purephotonicscontrol-0.0.0.dist-info/top_level.txt
purephotonicscontrol-0.0.0.dist-info/RECORD
