Metadata-Version: 2.1
Name: purephotonicscontrol
Version: 0.0.0
Summary: A package to control PurePhotonics lasers
Home-page: https://bitbucket.org/matthewberrington/purephotonicscontrol
Author: Matthew Berrington
Author-email: berrington95@gmail.com
License: UNKNOWN
Platform: UNKNOWN
Classifier: Programming Language :: Python :: 3
Classifier: License :: OSI Approved :: MIT License
Classifier: Operating System :: OS Independent
Requires-Dist: pyserial
Requires-Dist: numpy
